Week1 (Working on RTL and yosys synthesis)/Ripple carry adder 8bit/ripple_carry_adder_8bit.v

module full_adder (
    input  wire a,  
    input  wire b,    
    input  wire c,    
    output wire sum,  
    output wire co     
);

    assign sum = a ^ b ^ c;
    assign co  = (a & b) | (b & c) | (a & c);

endmodule




module ripple_carry_adder_8bit (input [7:0] A , input [7:0] B , output [8:0] sum);
wire [7:0] int_sum;
wire [7:0]int_co;

genvar i;
generate
	for (i = 1 ; i < 8; i=i+1) begin
		full_adder u1 (.a(A[i]),.b(B[i]),.c(int_co[i-1]),.co(int_co[i]),.sum(int_sum[i]));
	end

endgenerate
full_adder u2 (.a(A[0]),.b(B[0]),.c(1'b0),.co(int_co[0]),.sum(int_sum[0]));


assign sum[7:0] = int_sum;
assign sum[8] = int_co[7];
endmodule

Week1 (Working on RTL and yosys synthesis)/Ripple carry adder 8bit/ripple_8bit_tb.v
`timescale 1ns / 1ps
module ripple_carry_adder_8bit_tb;
	reg clk, reset   ;
	reg [7:0] num1 ;
	reg [7:0] num2;
	wire [8:0] sum_out;
	ripple_carry_adder_8bit uut (
		.A(num1),
		.B(num2),
		.sum(sum_out)
	);

	initial begin
	$dumpfile("ripple_carry_adder_8bit_tb.vcd");
	$dumpvars(0,ripple_carry_adder_8bit_tb);
	// Initialize Inputs
	clk = 0;
	reset = 0;
	reset = 1; #1;
	reset = 0; #10;
	#30000 $finish;
	end

always #10 clk = ~clk;


always @ (clk,reset)
begin
	if(reset)
	begin
		num1 <= 8'b0;
		num2 <= 8'b0;
	end
	else
	begin
		num1 = num1 + 1;
		if(num1[3:0] == 4'b1111)
			num2 = num2+1;	
	end

end


endmodule

Week1 (Working on RTL and yosys synthesis)/Ripple carry adder 8bit/ripple_carry_adder_8bit_tb.vcd
$date
	Sun Sep 28 10:44:13 2025
$end
$version
	Icarus Verilog
$end
$timescale
	1ps
$end
$scope module ripple_carry_adder_8bit_tb $end
$var wire 9 ! sum_out [8:0] $end
$var reg 1 " clk $end
$var reg 8 # num1 [7:0] $end
$var reg 8 $ num2 [7:0] $end
$var reg 1 % reset $end
$scope module uut $end
$var wire 8 & A [7:0] $end
$var wire 8 ' B [7:0] $end
$var wire 9 ( sum [8:0] $end
$var wire 8 ) int_sum [7:0] $end
$var wire 8 * int_co [7:0] $end
$scope begin genblk1[1] $end
$var parameter 2 + i $end
$scope module u1 $end
$var wire 1 , a $end
$var wire 1 - b $end
$var wire 1 . c $end
$var wire 1 / co $end
$var wire 1 0 sum $end
$upscope $end
$upscope $end
$scope begin genblk1[2] $end
$var parameter 3 1 i $end
$scope module u1 $end
$var wire 1 2 a $end
$var wire 1 3 b $end
$var wire 1 4 c $end
$var wire 1 5 co $end
$var wire 1 6 sum $end
$upscope $end
$upscope $end
$scope begin genblk1[3] $end
$var parameter 3 7 i $end
$scope module u1 $end
$var wire 1 8 a $end
$var wire 1 9 b $end
$var wire 1 : c $end
$var wire 1 ; co $end
$var wire 1 < sum $end
$upscope $end
$upscope $end
$scope begin genblk1[4] $end
$var parameter 4 = i $end
$scope module u1 $end
$var wire 1 > a $end
$var wire 1 ? b $end
$var wire 1 @ c $end
$var wire 1 A co $end
$var wire 1 B sum $end
$upscope $end
$upscope $end
$scope begin genblk1[5] $end
$var parameter 4 C i $end
$scope module u1 $end
$var wire 1 D a $end
$var wire 1 E b $end
$var wire 1 F c $end
$var wire 1 G co $end
$var wire 1 H sum $end
$upscope $end
$upscope $end
$scope begin genblk1[6] $end
$var parameter 4 I i $end
$scope module u1 $end
$var wire 1 J a $end
$var wire 1 K b $end
$var wire 1 L c $end
$var wire 1 M co $end
$var wire 1 N sum $end
$upscope $end
$upscope $end
$scope begin genblk1[7] $end
$var parameter 4 O i $end
$scope module u1 $end
$var wire 1 P a $end
$var wire 1 Q b $end
$var wire 1 R c $end
$var wire 1 S co $end
$var wire 1 T sum $end
$upscope $end
$upscope $end
$scope module u2 $end
$var wire 1 U a $end
$var wire 1 V b $end
$var wire 1 W c $end
$var wire 1 X co $end
$var wire 1 Y sum $end
$upscope $end
$upscope $end
$upscope $end
$enddefinitions $end
$comment Show the parameter values. $end
$dumpall
b111 O
b110 I
b101 C
b100 =
b11 7
b10 1
b1 +
$end
#0
$dumpvars
0Y
0X
0W
0V
0U
0T
0S
0R
0Q
0P
0N
0M
0L
0K
0J
0H
0G
0F
0E
0D
0B
0A
0@
0?
0>
0<
0;
0:
09
08
06
05
04
03
02
00
0/
0.
0-
0,
b0 *
b0 )
b0 (
b0 '
b0 &
1%
b0 $
b0 #
0"
b0 !
$end
#1000
b1 !
b1 (
b1 )
1Y
1U
b1 #
b1 &
0%
#10000
10
b10 !
b10 (
b10 )
0Y
1,
0U
b10 #
b10 &
1"
#20000
b11 !
b11 (
b11 )
1Y
1U
b11 #
b11 &
0"
#30000
00
16
b100 !
b100 (
b100 )
0Y
0,
12
0U
b100 #
b100 &
1"
#40000
b101 !
b101 (
b101 )
1Y
1U
b101 #
b101 &
0"
#50000
10
b110 !
b110 (
b110 )
0Y
1,
0U
b110 #
b110 &
1"
#60000
b111 !
b111 (
b111 )
1Y
1U
b111 #
b111 &
0"
#70000
00
06
1<
b1000 !
b1000 (
b1000 )
0Y
0,
02
18
0U
b1000 #
b1000 &
1"
#80000
b1001 !
b1001 (
b1001 )
1Y
1U
b1001 #
b1001 &
0"
#90000
10
b1010 !
b1010 (
b1010 )
0Y
1,
0U
b1010 #
b1010 &
1"
#100000
b1011 !
b1011 (
b1011 )
1Y
1U
b1011 #
b1011 &
0"
#110000
00
16
b1100 !
b1100 (
b1100 )
0Y
0,
12
0U
b1100 #
b1100 &
1"
#120000
b1101 !
b1101 (
b1101 )
1Y
1U
b1101 #
b1101 &
0"
#130000
10
b1110 !
b1110 (
b1110 )
0Y
1,
0U
b1110 #
b1110 &
1"
#140000
1B
1@
1;
0<
1:
15
06
14
1/
b10000 !
b10000 (
b10000 )
00
1.
b1111 *
1X
1V
1U
b1 $
b1 '
b1111 #
b1111 &
0"
#150000
0H
0.
04
0:
0@
0F
0X
00
0/
06
05
0<
0;
1B
b0 *
0A
b10001 !
b10001 (
b10001 )
1Y
0,
02
08
1>
0U
b10000 #
b10000 &
1"
#160000
10
1.
b1 *
1X
b10010 !
b10010 (
b10010 )
0Y
1U
b10001 #
b10001 &
0"
#170000
06
0.
04
0X
10
b0 *
0/
b10011 !
b10011 (
b10011 )
1Y
1,
0U
b10010 #
b10010 &
1"
#180000
16
14
1/
00
1.
b11 *
1X
b10100 !
b10100 (
b10100 )
0Y
1U
b10011 #
b10011 &
0"
#190000
0<
0.
04
0:
0X
00
0/
16
b0 *
05
b10101 !
b10101 (
b10101 )
1Y
0,
12
0U
b10100 #
b10100 &
1"
#200000
10
1.
b1 *
1X
b10110 !
b10110 (
b10110 )
0Y
1U
b10101 #
b10101 &
0"
#210000
0<
0:
05
16
0.
04
0X
10
b0 *
0/
b10111 !
b10111 (
b10111 )
1Y
1,
0U
b10110 #
b10110 &
1"
#220000
1<
1:
15
06
14
1/
00
1.
b111 *
1X
b11000 !
b11000 (
b11000 )
0Y
1U
b10111 #
b10111 &
0"
#230000
0H
0F
0A
1B
0.
04
0:
0@
0X
00
0/
06
05
1<
b0 *
0;
b11001 !
b11001 (
b11001 )
1Y
0,
02
18
0U
b11000 #
b11000 &
1"
#240000
10
1.
b1 *
1X
b11010 !
b11010 (
b11010 )
0Y
1U
b11001 #
b11001 &
0"
#250000
06
0.
04
0X
10
b0 *
0/
b11011 !
b11011 (
b11011 )
1Y
1,
0U
b11010 #
b11010 &
1"
#260000
16
14
1/
00
1.
b11 *
1X
b11100 !
b11100 (
b11100 )
0Y
1U
b11011 #
b11011 &
0"
#270000
0H
0F
0A
1B
0@
0;
1<
0.
04
0:
0X
00
0/
16
b0 *
05
b11101 !
b11101 (
b11101 )
1Y
0,
12
0U
b11100 #
b11100 &
1"
#280000
10
1.
b1 *
1X
b11110 !
b11110 (
b11110 )
0Y
1U
b11101 #
b11101 &
0"
#290000
0H
0F
0A
1B
0@
0;
1<
0:
05
16
0.
04
0X
10
b0 *
0/
b11111 !
b11111 (
b11111 )
1Y
1,
0U
b11110 #
b11110 &
1"
#300000
1H
1F
1A
0B
1@
1;
0<
1:
15
06
14
b11110 *
1/
b100001 !
b100001 (
b100001 )
00
1-
0V
1U
b10 $
b10 '
b11111 #
b11111 &
0"
#310000
04
0N
0/
0:
0@
0F
0L
10
06
05
0<
0;
0B
0A
1H
b0 *
0G
b100010 !
b100010 (
b100010 )
0Y
0,
02
08
0>
1D
0U
b100000 #
b100000 &
1"
#320000
b100011 !
b100011 (
b100011 )
1Y
1U
b100001 #
b100001 &
0"
#330000
16
14
b10 *
1/
00
b100100 !
b100100 (
b100100 )
0Y
1,
0U
b100010 #
b100010 &
1"
#340000
b100101 !
b100101 (
b100101 )
1Y
1U
b100011 #
b100011 &
0"
#350000
04
0<
0/
0:
10
16
b0 *
05
b100110 !
b100110 (
b100110 )
0Y
0,
12
0U
b100100 #
b100100 &
1"
#360000
b100111 !
b100111 (
b100111 )
1Y
1U
b100101 #
b100101 &
0"
#370000
1<
1:
15
06
14
b110 *
1/
00
b101000 !
b101000 (
b101000 )
0Y
1,
0U
b100110 #
b100110 &
1"
#380000
b101001 !
b101001 (
b101001 )
1Y
1U
b100111 #
b100111 &
0"
#390000
04
0B
0/
0:
0@
10
06
05
1<
b0 *
0;
b101010 !
b101010 (
b101010 )
0Y
0,
02
18
0U
b101000 #
b101000 &
1"
#400000
b101011 !
b101011 (
b101011 )
1Y
1U
b101001 #
b101001 &
0"
#410000
16
14
b10 *
1/
00
b101100 !
b101100 (
b101100 )
0Y
1,
0U
b101010 #
b101010 &
1"
#420000
b101101 !
b101101 (
b101101 )
1Y
1U
b101011 #
b101011 &
0"
#430000
0B
0@
0;
04
1<
0/
0:
10
16
b0 *
05
b101110 !
b101110 (
b101110 )
0Y
0,
12
0U
b101100 #
b101100 &
1"
#440000
b101111 !
b101111 (
b101111 )
1Y
1U
b101101 #
b101101 &
0"
#450000
1B
1@
1;
0<
1:
15
06
14
b1110 *
1/
00
b110000 !
b110000 (
b110000 )
0Y
1,
0U
b101110 #
b101110 &
1"
#460000
b110010 !
b110010 (
b110010 )
10
1.
b1111 *
1X
1V
1U
b11 $
b11 '
b101111 #
b101111 &
0"
#470000
04
0N
0/
0L
0G
1H
0.
0:
0@
0F
0X
10
06
05
0<
0;
1B
b0 *
0A
b110011 !
b110011 (
b110011 )
1Y
0,
02
08
1>
0U
b110000 #
b110000 &
1"
#480000
16
14
1/
00
1.
b11 *
1X
b110100 !
b110100 (
b110100 )
0Y
1U
b110001 #
b110001 &
0"
#490000
0.
b10 *
0X
00
b110101 !
b110101 (
b110101 )
1Y
1,
0U
b110010 #
b110010 &
1"
#500000
10
1.
b11 *
1X
b110110 !
b110110 (
b110110 )
0Y
1U
b110011 #
b110011 &
0"
#510000
04
0/
0<
0.
0:
0X
10
16
b0 *
05
b110111 !
b110111 (
b110111 )
1Y
0,
12
0U
b110100 #
b110100 &
1"
#520000
1<
1:
15
06
14
1/
00
1.
b111 *
1X
b111000 !
b111000 (
b111000 )
0Y
1U
b110101 #
b110101 &
0"
#530000
0.
b110 *
0X
00
b111001 !
b111001 (
b111001 )
1Y
1,
0U
b110110 #
b110110 &
1"
#540000
10
1.
b111 *
1X
b111010 !
b111010 (
b111010 )
0Y
1U
b110111 #
b110111 &
0"
#550000
0N
0L
0G
04
1H
0/
0F
0A
1B
0.
0:
0@
0X
10
06
05
1<
b0 *
0;
b111011 !
b111011 (
b111011 )
1Y
0,
02
18
0U
b111000 #
b111000 &
1"
#560000
16
14
1/
00
1.
b11 *
1X
b111100 !
b111100 (
b111100 )
0Y
1U
b111001 #
b111001 &
0"
#570000
0.
b10 *
0X
00
b111101 !
b111101 (
b111101 )
1Y
1,
0U
b111010 #
b111010 &
1"
#580000
10
1.
b11 *
1X
b111110 !
b111110 (
b111110 )
0Y
1U
b111011 #
b111011 &
0"
#590000
0N
0L
0G
1H
0F
0A
04
1B
0/
0@
0;
1<
0.
0:
0X
10
16
b0 *
05
b111111 !
b111111 (
b111111 )
1Y
0,
12
0U
b111100 #
b111100 &
1"
#600000
1N
1L
1G
0H
1F
1A
0B
1@
1;
0<
1:
15
06
14
1/
00
1.
b111111 *
1X
b1000000 !
b1000000 (
b1000000 )
0Y
1U
b111101 #
b111101 &
0"
#610000
0.
b111110 *
0X
00
b1000001 !
b1000001 (
b1000001 )
1Y
1,
0U
b111110 #
b111110 &
1"
#620000
04
b111100 *
0/
10
b1000011 !
b1000011 (
b1000011 )
06
0-
13
0V
1U
b100 $
b100 '
b111111 #
b111111 &
0"
#630000
0:
0T
05
0@
0F
0L
0R
00
16
0<
0;
0B
0A
0H
0G
1N
b0 *
0M
b1000100 !
b1000100 (
b1000100 )
0Y
0,
02
08
0>
0D
1J
0U
b1000000 #
b1000000 &
1"
#640000
b1000101 !
b1000101 (
b1000101 )
1Y
1U
b1000001 #
b1000001 &
0"
#650000
10
b1000110 !
b1000110 (
b1000110 )
0Y
1,
0U
b1000010 #
b1000010 &
1"
#660000
b1000111 !
b1000111 (
b1000111 )
1Y
1U
b1000011 #
b1000011 &
0"
#670000
1<
1:
b100 *
15
00
06
b1001000 !
b1001000 (
b1001000 )
0Y
0,
12
0U
b1000100 #
b1000100 &
1"
#680000
b1001001 !
b1001001 (
b1001001 )
1Y
1U
b1000101 #
b1000101 &
0"
#690000
10
b1001010 !
b1001010 (
b1001010 )
0Y
1,
0U
b1000110 #
b1000110 &
1"
#700000
b1001011 !
b1001011 (
b1001011 )
1Y
1U
b1000111 #
b1000111 &
0"
#710000
0:
0B
05
0@
00
16
1<
b0 *
0;
b1001100 !
b1001100 (
b1001100 )
0Y
0,
02
18
0U
b1001000 #
b1001000 &
1"
#720000
b1001101 !
b1001101 (
b1001101 )
1Y
1U
b1001001 #
b1001001 &
0"
#730000
10
b1001110 !
b1001110 (
b1001110 )
0Y
1,
0U
b1001010 #
b1001010 &
1"
#740000
b1001111 !
b1001111 (
b1001111 )
1Y
1U
b1001011 #
b1001011 &
0"
#750000
1B
1@
1;
0<
1:
b1100 *
15
00
06
b1010000 !
b1010000 (
b1010000 )
0Y
0,
12
0U
b1001100 #
b1001100 &
1"
#760000
b1010001 !
b1010001 (
b1010001 )
1Y
1U
b1001101 #
b1001101 &
0"
#770000
10
b1010010 !
b1010010 (
b1010010 )
0Y
1,
0U
b1001110 #
b1001110 &
1"
#780000
16
14
1/
b1010100 !
b1010100 (
b1010100 )
00
1.
b1111 *
1X
1V
1U
b101 $
b101 '
b1001111 #
b1001111 &
0"
#790000
0:
05
0H
0.
04
0@
0F
0X
00
0/
16
0<
0;
1B
b0 *
0A
b1010101 !
b1010101 (
b1010101 )
1Y
0,
02
08
1>
0U
b1010000 #
b1010000 &
1"
#800000
10
1.
b1 *
1X
b1010110 !
b1010110 (
b1010110 )
0Y
1U
b1010001 #
b1010001 &
0"
#810000
0<
0:
05
16
0.
04
0X
10
b0 *
0/
b1010111 !
b1010111 (
b1010111 )
1Y
1,
0U
b1010010 #
b1010010 &
1"
#820000
1<
1:
15
06
14
1/
00
1.
b111 *
1X
b1011000 !
b1011000 (
b1011000 )
0Y
1U
b1010011 #
b1010011 &
0"
#830000
0.
04
0X
00
b100 *
0/
06
b1011001 !
b1011001 (
b1011001 )
1Y
0,
12
0U
b1010100 #
b1010100 &
1"
#840000
10
1.
b101 *
1X
b1011010 !
b1011010 (
b1011010 )
0Y
1U
b1010101 #
b1010101 &
0"
#850000
06
0.
04
0X
10
b100 *
0/
b1011011 !
b1011011 (
b1011011 )
1Y
1,
0U
b1010110 #
b1010110 &
1"
#860000
16
14
1/
00
1.
b111 *
1X
b1011100 !
b1011100 (
b1011100 )
0Y
1U
b1010111 #
b1010111 &
0"
#870000
0:
0H
05
0F
0A
1B
0.
04
0@
0X
00
0/
16
1<
b0 *
0;
b1011101 !
b1011101 (
b1011101 )
1Y
0,
02
18
0U
b1011000 #
b1011000 &
1"
#880000
10
1.
b1 *
1X
b1011110 !
b1011110 (
b1011110 )
0Y
1U
b1011001 #
b1011001 &
0"
#890000
0H
0F
0A
1B
0@
0;
1<
0:
05
16
0.
04
0X
10
b0 *
0/
b1011111 !
b1011111 (
b1011111 )
1Y
1,
0U
b1011010 #
b1011010 &
1"
#900000
1H
1F
1A
0B
1@
1;
0<
1:
15
06
14
1/
00
1.
b11111 *
1X
b1100000 !
b1100000 (
b1100000 )
0Y
1U
b1011011 #
b1011011 &
0"
#910000
0.
04
0X
00
b11100 *
0/
06
b1100001 !
b1100001 (
b1100001 )
1Y
0,
12
0U
b1011100 #
b1011100 &
1"
#920000
10
1.
b11101 *
1X
b1100010 !
b1100010 (
b1100010 )
0Y
1U
b1011101 #
b1011101 &
0"
#930000
06
0.
04
0X
10
b11100 *
0/
b1100011 !
b1100011 (
b1100011 )
1Y
1,
0U
b1011110 #
b1011110 &
1"
#940000
16
14
b11110 *
1/
b1100101 !
b1100101 (
b1100101 )
00
1-
0V
1U
b110 $
b110 '
b1011111 #
b1011111 &
0"
#950000
0:
05
0T
0R
0M
04
1N
0/
0@
0F
0L
10
16
0<
0;
0B
0A
1H
b0 *
0G
b1100110 !
b1100110 (
b1100110 )
0Y
0,
02
08
0>
1D
0U
b1100000 #
b1100000 &
1"
#960000
b1100111 !
b1100111 (
b1100111 )
1Y
1U
b1100001 #
b1100001 &
0"
#970000
1<
1:
15
06
14
b110 *
1/
00
b1101000 !
b1101000 (
b1101000 )
0Y
1,
0U
b1100010 #
b1100010 &
1"
#980000
b1101001 !
b1101001 (
b1101001 )
1Y
1U
b1100011 #
b1100011 &
0"
#990000
04
b100 *
0/
10
06
b1101010 !
b1101010 (
b1101010 )
0Y
0,
12
0U
b1100100 #
b1100100 &
1"
#1000000
b1101011 !
b1101011 (
b1101011 )
1Y
1U
b1100101 #
b1100101 &
0"
#1010000
16
14
b110 *
1/
00
b1101100 !
b1101100 (
b1101100 )
0Y
1,
0U
b1100110 #
b1100110 &
1"
#1020000
b1101101 !
b1101101 (
b1101101 )
1Y
1U
b1100111 #
b1100111 &
0"
#1030000
0:
05
04
0B
0/
0@
10
16
1<
b0 *
0;
b1101110 !
b1101110 (
b1101110 )
0Y
0,
02
18
0U
b1101000 #
b1101000 &
1"
#1040000
b1101111 !
b1101111 (
b1101111 )
1Y
1U
b1101001 #
b1101001 &
0"
#1050000
1B
1@
1;
0<
1:
15
06
14
b1110 *
1/
00
b1110000 !
b1110000 (
b1110000 )
0Y
1,
0U
b1101010 #
b1101010 &
1"
#1060000
b1110001 !
b1110001 (
b1110001 )
1Y
1U
b1101011 #
b1101011 &
0"
#1070000
04
b1100 *
0/
10
06
b1110010 !
b1110010 (
b1110010 )
0Y
0,
12
0U
b1101100 #
b1101100 &
1"
#1080000
b1110011 !
b1110011 (
b1110011 )
1Y
1U
b1101101 #
b1101101 &
0"
#1090000
16
14
b1110 *
1/
00
b1110100 !
b1110100 (
b1110100 )
0Y
1,
0U
b1101110 #
b1101110 &
1"
#1100000
b1110110 !
b1110110 (
b1110110 )
10
1.
b1111 *
1X
1V
1U
b111 $
b111 '
b1101111 #
b1101111 &
0"
#1110000
0:
05
0T
0R
0M
04
1N
0/
0L
0G
1H
0.
0@
0F
0X
10
16
0<
0;
1B
b0 *
0A
b1110111 !
b1110111 (
b1110111 )
1Y
0,
02
08
1>
0U
b1110000 #
b1110000 &
1"
#1120000
1<
1:
15
06
14
1/
00
1.
b111 *
1X
b1111000 !
b1111000 (
b1111000 )
0Y
1U
b1110001 #
b1110001 &
0"
#1130000
0.
b110 *
0X
00
b1111001 !
b1111001 (
b1111001 )
1Y
1,
0U
b1110010 #
b1110010 &
1"
#1140000
10
1.
b111 *
1X
b1111010 !
b1111010 (
b1111010 )
0Y
1U
b1110011 #
b1110011 &
0"
#1150000
04
0/
0.
b100 *
0X
10
06
b1111011 !
b1111011 (
b1111011 )
1Y
0,
12
0U
b1110100 #
b1110100 &
1"
#1160000
16
14
1/
00
1.
b111 *
1X
b1111100 !
b1111100 (
b1111100 )
0Y
1U
b1110101 #
b1110101 &
0"
#1170000
0.
b110 *
0X
00
b1111101 !
b1111101 (
b1111101 )
1Y
1,
0U
b1110110 #
b1110110 &
1"
#1180000
10
1.
b111 *
1X
b1111110 !
b1111110 (
b1111110 )
0Y
1U
b1110111 #
b1110111 &
0"
#1190000
0T
0R
0:
0M
05
1N
0L
0G
04
1H
0/
0F
0A
1B
0.
0@
0X
10
16
1<
b0 *
0;
b1111111 !
b1111111 (
b1111111 )
1Y
0,
02
18
0U
b1111000 #
b1111000 &
1"
#1200000
1T
1R
1M
0N
1L
1G
0H
1F
1A
0B
1@
1;
0<
1:
15
06
14
1/
00
1.
b1111111 *
1X
b10000000 !
b10000000 (
b10000000 )
0Y
1U
b1111001 #
b1111001 &
0"
#1210000
0.
b1111110 *
0X
00
b10000001 !
b10000001 (
b10000001 )
1Y
1,
0U
b1111010 #
b1111010 &
1"
#1220000
10
1.
b1111111 *
1X
b10000010 !
b10000010 (
b10000010 )
0Y
1U
b1111011 #
b1111011 &
0"
#1230000
04
0/
0.
b1111100 *
0X
10
06
b10000011 !
b10000011 (
b10000011 )
1Y
0,
12
0U
b1111100 #
b1111100 &
1"
#1240000
16
14
1/
00
1.
b1111111 *
1X
b10000100 !
b10000100 (
b10000100 )
0Y
1U
b1111101 #
b1111101 &
0"
#1250000
0.
b1111110 *
0X
00
b10000101 !
b10000101 (
b10000101 )
1Y
1,
0U
b1111110 #
b1111110 &
1"
#1260000
0:
05
04
b1111000 *
0/
10
16
b10000111 !
b10000111 (
b10000111 )
0<
0-
03
19
0V
1U
b1000 $
b1000 '
b1111111 #
b1111111 &
0"
#1270000
0@
0;
0F
0L
0R
00
06
1<
0B
0A
0H
0G
0N
0M
1T
b0 *
0S
b10001000 !
b10001000 (
b10001000 )
0Y
0,
02
08
0>
0D
0J
1P
0U
b10000000 #
b10000000 &
1"
#1280000
b10001001 !
b10001001 (
b10001001 )
1Y
1U
b10000001 #
b10000001 &
0"
#1290000
10
b10001010 !
b10001010 (
b10001010 )
0Y
1,
0U
b10000010 #
b10000010 &
1"
#1300000
b10001011 !
b10001011 (
b10001011 )
1Y
1U
b10000011 #
b10000011 &
0"
#1310000
00
16
b10001100 !
b10001100 (
b10001100 )
0Y
0,
12
0U
b10000100 #
b10000100 &
1"
#1320000
b10001101 !
b10001101 (
b10001101 )
1Y
1U
b10000101 #
b10000101 &
0"
#1330000
10
b10001110 !
b10001110 (
b10001110 )
0Y
1,
0U
b10000110 #
b10000110 &
1"
#1340000
b10001111 !
b10001111 (
b10001111 )
1Y
1U
b10000111 #
b10000111 &
0"
#1350000
1B
1@
b1000 *
1;
00
06
0<
b10010000 !
b10010000 (
b10010000 )
0Y
0,
02
18
0U
b10001000 #
b10001000 &
1"
#1360000
b10010001 !
b10010001 (
b10010001 )
1Y
1U
b10001001 #
b10001001 &
0"
#1370000
10
b10010010 !
b10010010 (
b10010010 )
0Y
1,
0U
b10001010 #
b10001010 &
1"
#1380000
b10010011 !
b10010011 (
b10010011 )
1Y
1U
b10001011 #
b10001011 &
0"
#1390000
00
16
b10010100 !
b10010100 (
b10010100 )
0Y
0,
12
0U
b10001100 #
b10001100 &
1"
#1400000
b10010101 !
b10010101 (
b10010101 )
1Y
1U
b10001101 #
b10001101 &
0"
#1410000
10
b10010110 !
b10010110 (
b10010110 )
0Y
1,
0U
b10001110 #
b10001110 &
1"
#1420000
1<
1:
15
06
14
1/
b10011000 !
b10011000 (
b10011000 )
00
1.
b1111 *
1X
1V
1U
b1001 $
b1001 '
b10001111 #
b10001111 &
0"
#1430000
0@
0;
0H
0.
04
0:
0F
0X
00
0/
06
05
1<
1B
b0 *
0A
b10011001 !
b10011001 (
b10011001 )
1Y
0,
02
08
1>
0U
b10010000 #
b10010000 &
1"
#1440000
10
1.
b1 *
1X
b10011010 !
b10011010 (
b10011010 )
0Y
1U
b10010001 #
b10010001 &
0"
#1450000
06
0.
04
0X
10
b0 *
0/
b10011011 !
b10011011 (
b10011011 )
1Y
1,
0U
b10010010 #
b10010010 &
1"
#1460000
16
14
1/
00
1.
b11 *
1X
b10011100 !
b10011100 (
b10011100 )
0Y
1U
b10010011 #
b10010011 &
0"
#1470000
0H
0F
0A
1B
0@
0;
1<
0.
04
0:
0X
00
0/
16
b0 *
05
b10011101 !
b10011101 (
b10011101 )
1Y
0,
12
0U
b10010100 #
b10010100 &
1"
#1480000
10
1.
b1 *
1X
b10011110 !
b10011110 (
b10011110 )
0Y
1U
b10010101 #
b10010101 &
0"
#1490000
0H
0F
0A
1B
0@
0;
1<
0:
05
16
0.
04
0X
10
b0 *
0/
b10011111 !
b10011111 (
b10011111 )
1Y
1,
0U
b10010110 #
b10010110 &
1"
#1500000
1H
1F
1A
0B
1@
1;
0<
1:
15
06
14
1/
00
1.
b11111 *
1X
b10100000 !
b10100000 (
b10100000 )
0Y
1U
b10010111 #
b10010111 &
0"
#1510000
0.
04
0:
0X
00
0/
06
b11000 *
05
0<
b10100001 !
b10100001 (
b10100001 )
1Y
0,
02
18
0U
b10011000 #
b10011000 &
1"
#1520000
10
1.
b11001 *
1X
b10100010 !
b10100010 (
b10100010 )
0Y
1U
b10011001 #
b10011001 &
0"
#1530000
06
0.
04
0X
10
b11000 *
0/
b10100011 !
b10100011 (
b10100011 )
1Y
1,
0U
b10011010 #
b10011010 &
1"
#1540000
16
14
1/
00
1.
b11011 *
1X
b10100100 !
b10100100 (
b10100100 )
0Y
1U
b10011011 #
b10011011 &
0"
#1550000
0<
0.
04
0:
0X
00
0/
16
b11000 *
05
b10100101 !
b10100101 (
b10100101 )
1Y
0,
12
0U
b10011100 #
b10011100 &
1"
#1560000
10
1.
b11001 *
1X
b10100110 !
b10100110 (
b10100110 )
0Y
1U
b10011101 #
b10011101 &
0"
#1570000
0<
0:
05
16
0.
04
0X
10
b11000 *
0/
b10100111 !
b10100111 (
b10100111 )
1Y
1,
0U
b10011110 #
b10011110 &
1"
#1580000
1<
1:
15
06
14
b11110 *
1/
b10101001 !
b10101001 (
b10101001 )
00
1-
0V
1U
b1010 $
b1010 '
b10011111 #
b10011111 &
0"
#1590000
0@
0;
04
0N
0/
0:
0F
0L
10
06
05
1<
0B
0A
1H
b0 *
0G
b10101010 !
b10101010 (
b10101010 )
0Y
0,
02
08
0>
1D
0U
b10100000 #
b10100000 &
1"
#1600000
b10101011 !
b10101011 (
b10101011 )
1Y
1U
b10100001 #
b10100001 &
0"
#1610000
16
14
b10 *
1/
00
b10101100 !
b10101100 (
b10101100 )
0Y
1,
0U
b10100010 #
b10100010 &
1"
#1620000
b10101101 !
b10101101 (
b10101101 )
1Y
1U
b10100011 #
b10100011 &
0"
#1630000
0B
0@
0;
04
1<
0/
0:
10
16
b0 *
05
b10101110 !
b10101110 (
b10101110 )
0Y
0,
12
0U
b10100100 #
b10100100 &
1"
#1640000
b10101111 !
b10101111 (
b10101111 )
1Y
1U
b10100101 #
b10100101 &
0"
#1650000
1B
1@
1;
0<
1:
15
06
14
b1110 *
1/
00
b10110000 !
b10110000 (
b10110000 )
0Y
1,
0U
b10100110 #
b10100110 &
1"
#1660000
b10110001 !
b10110001 (
b10110001 )
1Y
1U
b10100111 #
b10100111 &
0"
#1670000
04
0/
0:
10
06
b1000 *
05
0<
b10110010 !
b10110010 (
b10110010 )
0Y
0,
02
18
0U
b10101000 #
b10101000 &
1"
#1680000
b10110011 !
b10110011 (
b10110011 )
1Y
1U
b10101001 #
b10101001 &
0"
#1690000
16
14
b1010 *
1/
00
b10110100 !
b10110100 (
b10110100 )
0Y
1,
0U
b10101010 #
b10101010 &
1"
#1700000
b10110101 !
b10110101 (
b10110101 )
1Y
1U
b10101011 #
b10101011 &
0"
#1710000
04
0<
0/
0:
10
16
b1000 *
05
b10110110 !
b10110110 (
b10110110 )
0Y
0,
12
0U
b10101100 #
b10101100 &
1"
#1720000
b10110111 !
b10110111 (
b10110111 )
1Y
1U
b10101101 #
b10101101 &
0"
#1730000
1<
1:
15
06
14
b1110 *
1/
00
b10111000 !
b10111000 (
b10111000 )
0Y
1,
0U
b10101110 #
b10101110 &
1"
#1740000
b10111010 !
b10111010 (
b10111010 )
10
1.
b1111 *
1X
1V
1U
b1011 $
b1011 '
b10101111 #
b10101111 &
0"
#1750000
04
0@
0N
0/
0;
0L
0G
1H
0.
0:
0F
0X
10
06
05
1<
1B
b0 *
0A
b10111011 !
b10111011 (
b10111011 )
1Y
0,
02
08
1>
0U
b10110000 #
b10110000 &
1"
#1760000
16
14
1/
00
1.
b11 *
1X
b10111100 !
b10111100 (
b10111100 )
0Y
1U
b10110001 #
b10110001 &
0"
#1770000
0.
b10 *
0X
00
b10111101 !
b10111101 (
b10111101 )
1Y
1,
0U
b10110010 #
b10110010 &
1"
#1780000
10
1.
b11 *
1X
b10111110 !
b10111110 (
b10111110 )
0Y
1U
b10110011 #
b10110011 &
0"
#1790000
0N
0L
0G
1H
0F
0A
1B
04
0@
0/
0;
1<
0.
0:
0X
10
16
b0 *
05
b10111111 !
b10111111 (
b10111111 )
1Y
0,
12
0U
b10110100 #
b10110100 &
1"
#1800000
1N
1L
1G
0H
1F
1A
0B
1@
1;
0<
1:
15
06
14
1/
00
1.
b111111 *
1X
b11000000 !
b11000000 (
b11000000 )
0Y
1U
b10110101 #
b10110101 &
0"
#1810000
0.
b111110 *
0X
00
b11000001 !
b11000001 (
b11000001 )
1Y
1,
0U
b10110110 #
b10110110 &
1"
#1820000
10
1.
b111111 *
1X
b11000010 !
b11000010 (
b11000010 )
0Y
1U
b10110111 #
b10110111 &
0"
