Week1 (Working on RTL and yosys synthesis)/d_flipflop/d_flop_sync_async/dff_sync_async.v
module dff_sync_async(
    input wire clk,
    input wire d,
    input wire sync_rst,    
    input wire async_rst,    
    output reg q
);
    always @(posedge clk or posedge async_rst) begin
        if (async_rst)
            q <= 1'b0;
        else begin
            if (sync_rst)
                q <= 1'b0;
            else
                q <= d;
        end
    end
endmodule

Week1 (Working on RTL and yosys synthesis)/d_flipflop/d_flop_sync_async/dff_sync_async_tb.v
`timescale 1ns/1ps

module dff_sync_async_tb;
    reg clk;
    reg d;
    reg sync_rst;
    reg async_rst;
    wire q;

    dff_sync_async uut (
        .clk(clk),
        .d(d),
        .sync_rst(sync_rst),
        .async_rst(async_rst),
        .q(q)
    );

    always #5 clk = ~clk;

    initial begin
        $dumpfile("dff_sync_async_tb.vcd");
        $dumpvars(0, dff_sync_async_tb);
       clk = 0;
       sync_rst = 0; async_rst = 0; d = 1; #13
       sync_rst = 1; async_rst = 0; d = 1; #14
       sync_rst = 0; async_rst = 0; d = 1; #15
       sync_rst = 0; async_rst = 0; d = 1; #8
       sync_rst = 0; async_rst = 1; d = 1; #5
       sync_rst = 0; async_rst = 0; d = 1; #10
       $finish; 
  end
endmodule

Week1 (Working on RTL and yosys synthesis)/d_flipflop/d_flop_sync_async/dff_sync_async_tb.vcd
$date
	Sat Sep 27 17:24:41 2025
$end
$version
	Icarus Verilog
$end
$timescale
	1ps
$end
$scope module dff_sync_async_tb $end
$var wire 1 ! q $end
$var reg 1 " async_rst $end
$var reg 1 # clk $end
$var reg 1 $ d $end
$var reg 1 % sync_rst $end
$scope module uut $end
$var wire 1 " async_rst $end
$var wire 1 # clk $end
$var wire 1 $ d $end
$var wire 1 % sync_rst $end
$var reg 1 ! q $end
$upscope $end
$upscope $end
$enddefinitions $end
$comment Show the parameter values. $end
$dumpall
$end
#0
$dumpvars
0%
1$
0#
0"
x!
$end
#5000
1!
1#
#10000
0#
#13000
1%
#15000
0!
1#
#20000
0#
#25000
1#
#27000
0%
#30000
0#
#35000
1!
1#
#40000
0#
#45000
1#
#50000
0!
0#
1"
#55000
1!
1#
0"
