Week1 (Working on RTL and yosys synthesis)/d_flipflop/d_flop_sync/dff_sync.v
module dff_sync (
    input wire clk,
    input wire d,
    input wire rst,    // synchronous reset
    input wire set,    // synchronous set
    output reg q
);
    always @(posedge clk) begin
        if (rst)
            q <= 1'b0;
        else if (set)
            q <= 1'b1;
        else
            q <= d;
    end
endmodule

Week1 (Working on RTL and yosys synthesis)/d_flipflop/d_flop_sync/dff_sync_tb.v
`timescale 1ns/1ps

module dff_sync_tb;
    reg clk;
    reg d;
    reg rst;
    reg set;
    wire q;

    dff_sync uut (
        .clk(clk),
        .d(d),
        .rst(rst),
        .set(set),
        .q(q)
    );

    always #5 clk = ~clk;

    initial begin
        $dumpfile("dff_sync_tb.vcd");
        $dumpvars(0, dff_sync_tb);
        clk =0;
        rst = 0; set = 0; d = 1; #15
        rst = 1; set = 0; d = 1; #15
        rst = 0; set = 0; d = 1; #15
        rst = 0; set = 0; d = 1; #15
        rst = 0; set = 0; d = 0; #15
        rst = 0; set = 1; d = 0; #15
           $finish;
  end
endmodule

Week1 (Working on RTL and yosys synthesis)/d_flipflop/d_flop_sync/dff_sync_tb.vcd
$date
	Sat Sep 27 17:17:35 2025
$end
$version
	Icarus Verilog
$end
$timescale
	1ps
$end
$scope module dff_sync_tb $end
$var wire 1 ! q $end
$var reg 1 " clk $end
$var reg 1 # d $end
$var reg 1 $ rst $end
$var reg 1 % set $end
$scope module uut $end
$var wire 1 " clk $end
$var wire 1 # d $end
$var wire 1 $ rst $end
$var wire 1 % set $end
$var reg 1 ! q $end
$upscope $end
$upscope $end
$enddefinitions $end
$comment Show the parameter values. $end
$dumpall
$end
#0
$dumpvars
0%
0$
1#
0"
x!
$end
#5000
1!
1"
#10000
0"
#15000
0!
1"
1$
#20000
0"
#25000
1"
#30000
0"
0$
#35000
1!
1"
#40000
0"
#45000
1"
#50000
0"
#55000
1"
#60000
0"
0#
#65000
0!
1"
#70000
0"
#75000
1!
1"
1%
