Week1 (Working on RTL and yosys synthesis)/Demux_1:8_generate/demux_1to8_gen.v

module demux_1to8_gen (output reg [7:0] out , input [2:0] sel  , input i);
integer k;
always @ (*)
begin
out = 8'b0;
for(k = 0; k < 8; k++) begin
	if(k == sel)
		out[k] = i;
end
end
endmodule

Week1 (Working on RTL and yosys synthesis)/Demux_1:8_generate/demux_1to8_gen_tb.v


`timescale 1ns / 1ps
module demux_1to8_gen_tb;
	reg i;
	reg [2:0] sel;
	reg clk,reset;
	wire [7:0] out;
	demux_1to8_gen uut (
		.sel(sel),
		.out(out),
		.i(i)
	);

	initial begin
	$dumpfile("demux_1to8_gen_tb.vcd");
	$dumpvars(0,demux_1to8_gen_tb);
	i = 1'b0;
	clk = 1'b0;
	reset = 1'b0 ;  #1;
	reset = 1'b1 ;  #10;
	reset = 1'b0;

	#3900 $finish;
	end

always #17 i = ~i;
always #300 clk = ~clk;

always @ (posedge clk , posedge reset)
begin
	if(reset)
		sel <= 3'b000;
	else
		sel <= sel + 1;
end

endmodule

Week1 (Working on RTL and yosys synthesis)/Demux_1:8_generate/demux_1to8_gen_tb.vcd
$date
	Sun Sep 28 10:00:52 2025
$end
$version
	Icarus Verilog
$end
$timescale
	1ps
$end
$scope module demux_1to8_gen_tb $end
$var wire 8 ! out [7:0] $end
$var reg 1 " clk $end
$var reg 1 # i $end
$var reg 1 $ reset $end
$var reg 3 % sel [2:0] $end
$scope module uut $end
$var wire 1 # i $end
$var wire 3 & sel [2:0] $end
$var reg 8 ' out [7:0] $end
$var integer 32 ( k [31:0] $end
$upscope $end
$upscope $end
$enddefinitions $end
$comment Show the parameter values. $end
$dumpall
$end
#0
$dumpvars
b1000 (
b0 '
bx &
bx %
0$
0#
0"
b0 !
$end
#1000
b1000 (
b0 %
b0 &
1$
#11000
0$
#17000
b1 !
b1 '
b1000 (
1#
#34000
b1000 (
b0 !
b0 '
0#
#51000
b1 !
b1 '
b1000 (
1#
#68000
b1000 (
b0 !
b0 '
0#
#85000
b1 !
b1 '
b1000 (
1#
#102000
b1000 (
b0 !
b0 '
0#
#119000
b1 !
b1 '
b1000 (
1#
#136000
b1000 (
b0 !
b0 '
0#
#153000
b1 !
b1 '
b1000 (
1#
#170000
b1000 (
b0 !
b0 '
0#
#187000
b1 !
b1 '
b1000 (
1#
#204000
b1000 (
b0 !
b0 '
0#
#221000
b1 !
b1 '
b1000 (
1#
#238000
b1000 (
b0 !
b0 '
0#
#255000
b1 !
b1 '
b1000 (
1#
#272000
b1000 (
b0 !
b0 '
0#
#289000
b1 !
b1 '
b1000 (
1#
#300000
b1000 (
b10 !
b10 '
b1 %
b1 &
1"
#306000
b1000 (
b0 !
b0 '
0#
#323000
b10 !
b10 '
b1000 (
1#
#340000
b1000 (
b0 !
b0 '
0#
#357000
b10 !
b10 '
b1000 (
1#
#374000
b1000 (
b0 !
b0 '
0#
#391000
b10 !
b10 '
b1000 (
1#
#408000
b1000 (
b0 !
b0 '
0#
#425000
b10 !
b10 '
b1000 (
1#
#442000
b1000 (
b0 !
b0 '
0#
#459000
b10 !
b10 '
b1000 (
1#
#476000
b1000 (
b0 !
b0 '
0#
#493000
b10 !
b10 '
b1000 (
1#
#510000
b1000 (
b0 !
b0 '
0#
#527000
b10 !
b10 '
b1000 (
1#
#544000
b1000 (
b0 !
b0 '
0#
#561000
b10 !
b10 '
b1000 (
1#
#578000
b1000 (
b0 !
b0 '
0#
#595000
b10 !
b10 '
b1000 (
1#
#600000
0"
#612000
b1000 (
b0 !
b0 '
0#
#629000
b10 !
b10 '
b1000 (
1#
#646000
b1000 (
b0 !
b0 '
0#
#663000
b10 !
b10 '
b1000 (
1#
#680000
b1000 (
b0 !
b0 '
0#
#697000
b10 !
b10 '
b1000 (
1#
#714000
b1000 (
b0 !
b0 '
0#
#731000
b10 !
b10 '
b1000 (
1#
#748000
b1000 (
b0 !
b0 '
0#
#765000
b10 !
b10 '
b1000 (
1#
#782000
b1000 (
b0 !
b0 '
0#
#799000
b10 !
b10 '
b1000 (
1#
#816000
b1000 (
b0 !
b0 '
0#
#833000
b10 !
b10 '
b1000 (
1#
#850000
b1000 (
b0 !
b0 '
0#
#867000
b10 !
b10 '
b1000 (
1#
#884000
b1000 (
b0 !
b0 '
0#
#900000
b1000 (
b10 %
b10 &
1"
#901000
b100 !
b100 '
b1000 (
1#
#918000
b1000 (
b0 !
b0 '
0#
#935000
b100 !
b100 '
b1000 (
1#
#952000
b1000 (
b0 !
b0 '
0#
#969000
b100 !
b100 '
b1000 (
1#
#986000
b1000 (
b0 !
b0 '
0#
#1003000
b100 !
b100 '
b1000 (
1#
#1020000
b1000 (
b0 !
b0 '
0#
#1037000
b100 !
b100 '
b1000 (
1#
#1054000
b1000 (
b0 !
b0 '
0#
#1071000
b100 !
b100 '
b1000 (
1#
#1088000
b1000 (
b0 !
b0 '
0#
#1105000
b100 !
b100 '
b1000 (
1#
#1122000
b1000 (
b0 !
b0 '
0#
#1139000
b100 !
b100 '
b1000 (
1#
#1156000
b1000 (
b0 !
b0 '
0#
#1173000
b100 !
b100 '
b1000 (
1#
#1190000
b1000 (
b0 !
b0 '
0#
#1200000
0"
#1207000
b100 !
b100 '
b1000 (
1#
#1224000
b1000 (
b0 !
b0 '
0#
#1241000
b100 !
b100 '
b1000 (
1#
#1258000
b1000 (
b0 !
b0 '
0#
#1275000
b100 !
b100 '
b1000 (
1#
#1292000
b1000 (
b0 !
b0 '
0#
#1309000
b100 !
b100 '
b1000 (
1#
#1326000
b1000 (
b0 !
b0 '
0#
#1343000
b100 !
b100 '
b1000 (
1#
#1360000
b1000 (
b0 !
b0 '
0#
#1377000
b100 !
b100 '
b1000 (
1#
#1394000
b1000 (
b0 !
b0 '
0#
#1411000
b100 !
b100 '
b1000 (
1#
#1428000
b1000 (
b0 !
b0 '
0#
#1445000
b100 !
b100 '
b1000 (
1#
#1462000
b1000 (
b0 !
b0 '
0#
#1479000
b100 !
b100 '
b1000 (
1#
#1496000
b1000 (
b0 !
b0 '
0#
#1500000
b1000 (
b11 %
b11 &
1"
#1513000
b1000 !
b1000 '
b1000 (
1#
#1530000
b1000 (
b0 !
b0 '
0#
#1547000
b1000 !
b1000 '
b1000 (
1#
#1564000
b1000 (
b0 !
b0 '
0#
#1581000
b1000 !
b1000 '
b1000 (
1#
#1598000
b1000 (
b0 !
b0 '
0#
#1615000
b1000 !
b1000 '
b1000 (
1#
#1632000
b1000 (
b0 !
b0 '
0#
#1649000
b1000 !
b1000 '
b1000 (
1#
#1666000
b1000 (
b0 !
b0 '
0#
#1683000
b1000 !
b1000 '
b1000 (
1#
#1700000
b1000 (
b0 !
b0 '
0#
#1717000
b1000 !
b1000 '
b1000 (
1#
#1734000
b1000 (
b0 !
b0 '
0#
#1751000
b1000 !
b1000 '
b1000 (
1#
#1768000
b1000 (
b0 !
b0 '
0#
#1785000
b1000 !
b1000 '
b1000 (
1#
#1800000
0"
#1802000
b1000 (
b0 !
b0 '
0#
#1819000
b1000 !
b1000 '
b1000 (
1#
#1836000
b1000 (
b0 !
b0 '
0#
#1853000
b1000 !
b1000 '
b1000 (
1#
#1870000
b1000 (
b0 !
b0 '
0#
#1887000
b1000 !
b1000 '
b1000 (
1#
#1904000
b1000 (
b0 !
b0 '
0#
#1921000
b1000 !
b1000 '
b1000 (
1#
#1938000
b1000 (
b0 !
b0 '
0#
#1955000
b1000 !
b1000 '
b1000 (
1#
#1972000
b1000 (
b0 !
b0 '
0#
#1989000
b1000 !
b1000 '
b1000 (
1#
#2006000
b1000 (
b0 !
b0 '
0#
#2023000
b1000 !
b1000 '
b1000 (
1#
#2040000
b1000 (
b0 !
b0 '
0#
#2057000
b1000 !
b1000 '
b1000 (
1#
#2074000
b1000 (
b0 !
b0 '
0#
#2091000
b1000 !
b1000 '
b1000 (
1#
#2100000
b1000 (
b10000 !
b10000 '
b100 %
b100 &
1"
#2108000
b1000 (
b0 !
b0 '
0#
#2125000
b10000 !
b10000 '
b1000 (
1#
#2142000
b1000 (
b0 !
b0 '
0#
#2159000
b10000 !
b10000 '
b1000 (
1#
#2176000
b1000 (
b0 !
b0 '
0#
#2193000
b10000 !
b10000 '
b1000 (
1#
#2210000
b1000 (
b0 !
b0 '
0#
#2227000
b10000 !
b10000 '
b1000 (
1#
#2244000
b1000 (
b0 !
b0 '
0#
#2261000
b10000 !
b10000 '
b1000 (
1#
#2278000
b1000 (
b0 !
b0 '
0#
#2295000
b10000 !
b10000 '
b1000 (
1#
#2312000
b1000 (
b0 !
b0 '
0#
#2329000
b10000 !
b10000 '
b1000 (
1#
#2346000
b1000 (
b0 !
b0 '
0#
#2363000
b10000 !
b10000 '
b1000 (
1#
#2380000
b1000 (
b0 !
b0 '
0#
#2397000
b10000 !
b10000 '
b1000 (
1#
#2400000
0"
#2414000
b1000 (
b0 !
b0 '
0#
#2431000
b10000 !
b10000 '
b1000 (
1#
#2448000
b1000 (
b0 !
b0 '
0#
#2465000
b10000 !
b10000 '
b1000 (
1#
#2482000
b1000 (
b0 !
b0 '
0#
#2499000
b10000 !
b10000 '
b1000 (
1#
#2516000
b1000 (
b0 !
b0 '
0#
#2533000
b10000 !
b10000 '
b1000 (
1#
#2550000
b1000 (
b0 !
b0 '
0#
#2567000
b10000 !
b10000 '
b1000 (
1#
#2584000
b1000 (
b0 !
b0 '
0#
#2601000
b10000 !
b10000 '
b1000 (
1#
#2618000
b1000 (
b0 !
b0 '
0#
#2635000
b10000 !
b10000 '
b1000 (
1#
#2652000
b1000 (
b0 !
b0 '
0#
#2669000
b10000 !
b10000 '
b1000 (
1#
#2686000
b1000 (
b0 !
b0 '
0#
#2700000
b1000 (
b101 %
b101 &
1"
#2703000
b100000 !
b100000 '
b1000 (
1#
#2720000
b1000 (
b0 !
b0 '
0#
#2737000
b100000 !
b100000 '
b1000 (
1#
#2754000
b1000 (
b0 !
b0 '
0#
#2771000
b100000 !
b100000 '
b1000 (
1#
#2788000
b1000 (
b0 !
b0 '
0#
#2805000
b100000 !
b100000 '
b1000 (
1#
#2822000
b1000 (
b0 !
b0 '
0#
#2839000
b100000 !
b100000 '
b1000 (
1#
#2856000
b1000 (
b0 !
b0 '
0#
#2873000
b100000 !
b100000 '
b1000 (
1#
#2890000
b1000 (
b0 !
b0 '
0#
#2907000
b100000 !
b100000 '
b1000 (
1#
#2924000
b1000 (
b0 !
b0 '
0#
#2941000
b100000 !
b100000 '
b1000 (
1#
#2958000
b1000 (
b0 !
b0 '
0#
#2975000
b100000 !
b100000 '
b1000 (
1#
#2992000
b1000 (
b0 !
b0 '
0#
#3000000
0"
#3009000
b100000 !
b100000 '
b1000 (
1#
#3026000
b1000 (
b0 !
b0 '
0#
#3043000
b100000 !
b100000 '
b1000 (
1#
#3060000
b1000 (
b0 !
b0 '
0#
#3077000
b100000 !
b100000 '
b1000 (
1#
#3094000
b1000 (
b0 !
b0 '
0#
#3111000
b100000 !
b100000 '
b1000 (
1#
#3128000
b1000 (
b0 !
b0 '
0#
#3145000
b100000 !
b100000 '
b1000 (
1#
#3162000
b1000 (
b0 !
b0 '
0#
#3179000
b100000 !
b100000 '
b1000 (
1#
#3196000
b1000 (
b0 !
b0 '
0#
#3213000
b100000 !
b100000 '
b1000 (
1#
#3230000
b1000 (
b0 !
b0 '
0#
#3247000
b100000 !
b100000 '
b1000 (
1#
#3264000
b1000 (
b0 !
b0 '
0#
#3281000
b100000 !
b100000 '
b1000 (
1#
#3298000
b1000 (
b0 !
b0 '
0#
#3300000
b1000 (
b110 %
b110 &
1"
#3315000
b1000000 !
b1000000 '
b1000 (
1#
#3332000
b1000 (
b0 !
b0 '
0#
#3349000
b1000000 !
b1000000 '
b1000 (
1#
#3366000
b1000 (
b0 !
b0 '
0#
#3383000
b1000000 !
b1000000 '
b1000 (
1#
#3400000
b1000 (
b0 !
b0 '
0#
#3417000
b1000000 !
b1000000 '
b1000 (
1#
#3434000
b1000 (
b0 !
b0 '
0#
#3451000
b1000000 !
b1000000 '
b1000 (
1#
#3468000
b1000 (
b0 !
b0 '
0#
#3485000
b1000000 !
b1000000 '
b1000 (
1#
#3502000
b1000 (
b0 !
b0 '
0#
#3519000
b1000000 !
b1000000 '
b1000 (
1#
#3536000
b1000 (
b0 !
b0 '
0#
#3553000
b1000000 !
b1000000 '
b1000 (
1#
#3570000
b1000 (
b0 !
b0 '
0#
#3587000
b1000000 !
b1000000 '
b1000 (
1#
#3600000
0"
#3604000
b1000 (
b0 !
b0 '
0#
#3621000
b1000000 !
b1000000 '
b1000 (
1#
#3638000
b1000 (
b0 !
b0 '
0#
#3655000
b1000000 !
b1000000 '
b1000 (
1#
#3672000
b1000 (
b0 !
b0 '
0#
#3689000
b1000000 !
b1000000 '
b1000 (
1#
#3706000
b1000 (
b0 !
b0 '
0#
#3723000
b1000000 !
b1000000 '
b1000 (
1#
#3740000
b1000 (
b0 !
b0 '
0#
#3757000
b1000000 !
b1000000 '
b1000 (
1#
#3774000
b1000 (
b0 !
b0 '
0#
#3791000
b1000000 !
b1000000 '
b1000 (
1#
#3808000
b1000 (
b0 !
b0 '
0#
#3825000
b1000000 !
b1000000 '
b1000 (
1#
#3842000
b1000 (
b0 !
b0 '
0#
#3859000
b1000000 !
b1000000 '
b1000 (
1#
#3876000
b1000 (
b0 !
b0 '
0#
#3893000
b1000000 !
b1000000 '
b1000 (
1#
#3900000
b1000 (
b10000000 !
b10000000 '
b111 %
b111 &
1"
#3910000
b1000 (
b0 !
b0 '
0#
